lab1/vending_machine2/change_state.v
`include "vending_machine_def.v"


module change_state(clk,reset_n,current_total_nxt,current_total,return_coin_nxt,o_return_coin);

	input clk;
	input reset_n;
	input [`kTotalBits-1:0] current_total_nxt;
	input [`kNumCoins-1:0] return_coin_nxt;
	output reg [`kNumCoins-1:0] o_return_coin;
	output reg [`kTotalBits-1:0] current_total;
	
	// Sequential circuit to reset or update the states
	always @(posedge clk ) begin
		if (!reset_n) begin
			// TODO: reset all states.
			current_total<=0;
			o_return_coin<=0;
		end
		else begin
			// TODO: update all states.
			current_total <= current_total_nxt ;
			o_return_coin <= return_coin_nxt;
		end
	end
endmodule

lab1/vending_machine2/calculate_current_state.v

`include "vending_machine_def.v"
	

module calculate_current_state(i_input_coin,i_select_item,i_trigger_return,item_price,coin_value,current_total,
		current_total_nxt,wait_time,o_available_item,o_output_item,return_coin_nxt);


	
	input [`kNumCoins-1:0] i_input_coin;
	input [`kNumItems-1:0]	i_select_item;			
	input i_trigger_return;
	input [31:0] item_price [`kNumItems-1:0];
	input [31:0] coin_value [`kNumCoins-1:0];	
	input [`kTotalBits-1:0] current_total;
	input [31:0] wait_time;
	output reg [`kNumItems-1:0] o_available_item,o_output_item;
	output reg  [`kTotalBits-1:0]current_total_nxt;
	output reg [`kNumCoins-1:0] return_coin_nxt;

	integer i;
	
	// Combinational logic for the next states   
	initial begin
		o_available_item = 0;
		o_output_item = 0;
		return_coin_nxt = 0;
		current_total_nxt = 0;
		i =0;
	end

	always @(*) begin
		// TODO: current_total_nxt
		return_coin_nxt = 0;
		o_output_item = 0;
		
		if(i_input_coin != 0) begin
			i=0;
			if(i_input_coin[0]!=0) begin
				current_total_nxt = current_total + coin_value[0];
			end
			else if(i_input_coin[1]!=0) begin
				current_total_nxt = current_total + coin_value[1];
			end
			else if(i_input_coin[2]!=0) begin
				current_total_nxt = current_total + coin_value[2];
			end
			else begin
				current_total_nxt = current_total;
			end
		end

		else if(i_select_item != 0) begin
				i=0;
				if(i_select_item[0] && o_available_item[0]) begin
					current_total_nxt = current_total - item_price[0];
					o_output_item[0]=1;
				end
				else if(i_select_item[1] && o_available_item[1]) begin
					current_total_nxt = current_total - item_price[1];
					o_output_item[1]=1;
				end
				else if(i_select_item[2] && o_available_item[2]) begin
					current_total_nxt = current_total - item_price[2];
					o_output_item[2]=1;
				end
				else if(i_select_item[3] && o_available_item[3]) begin
					current_total_nxt = current_total - item_price[3];
					o_output_item[3]=1;
				end
				else begin
					current_total_nxt = current_total;
					o_output_item = 0;
				end
		end
		else if(i_trigger_return == 1) begin
			if(i >= 7) begin
				if(current_total >= 1600) begin
					return_coin_nxt = 3'b111;
					current_total_nxt = current_total-1600;
				end
				else if(current_total >= 1500) begin
					return_coin_nxt = 3'b110;
					current_total_nxt = current_total-1500;
				end
				else if(current_total >= 1100) begin
					return_coin_nxt = 3'b101;
					current_total_nxt = current_total-1100;
				end
				else if(current_total >= 1000) begin
					return_coin_nxt = 3'b100;
					current_total_nxt = current_total-1000;
				end
				else if(current_total >= 600) begin
					return_coin_nxt = 3'b011;
					current_total_nxt = current_total-600;
				end
				else if(current_total >= 500) begin
					return_coin_nxt = 3'b010;
					current_total_nxt = current_total-500;
				end
				else if(current_total >= 100) begin
					return_coin_nxt = 3'b001;
					current_total_nxt = current_total-100;
				end
				else begin
					current_total_nxt = current_total;
				end
			end

			else begin
				current_total_nxt = current_total;
			end
			i = i+1;

		end

		else if($signed(wait_time) <= -1) begin
			i=0;
			if(current_total >= 1600) begin
            	return_coin_nxt = 3'b111;
            	current_total_nxt = current_total-1600;
        	end
			else if(current_total >= 1500) begin
				return_coin_nxt = 3'b110;
				current_total_nxt = current_total-1500;
			end
			else if(current_total >= 1100) begin
				return_coin_nxt = 3'b101;
				current_total_nxt = current_total-1100;
			end
			else if(current_total >= 1000) begin
				return_coin_nxt = 3'b100;
				current_total_nxt = current_total-1000;
			end
			else if(current_total >= 600) begin
				return_coin_nxt = 3'b011;
				current_total_nxt = current_total-600;
			end
			else if(current_total >= 500) begin
				return_coin_nxt = 3'b010;
				current_total_nxt = current_total-500;
			end
			else if(current_total >= 100) begin
				return_coin_nxt = 3'b001;
				current_total_nxt = current_total-100;
			end
			else begin
				current_total_nxt = current_total;
			end
		end
		else begin
			i=0;
			current_total_nxt = current_total;
		end

	end

	// Combinational logic for the outputs
	always @(*) begin
		// TODO: o_available_item
		if(current_total >= 2000) begin
			o_available_item = 4'b1111;
		end
		else if(current_total >= 1000) begin
			o_available_item = 4'b0111;
		end
		else if(current_total >= 500) begin
			o_available_item = 4'b0011;
		end
		else if(current_total >= 400) begin
			o_available_item=4'b0001;
		end
		else begin
			o_available_item = 4'b0000;
		end
	end
	


endmodule

lab1/vending_machine2/check_time_and_coin.v
`include "vending_machine_def.v"

	

module check_time_and_coin(i_input_coin,i_select_item,o_available_item,clk,reset_n,wait_time);
	input clk;
	input reset_n;
	input [`kNumCoins-1:0] i_input_coin;
	input [`kNumItems-1:0]	i_select_item;
	input [`kNumItems-1:0] o_available_item;

	output reg [31:0] wait_time;
	reg [31:0] wait_time_nxt;


	// initiate values
	initial begin
		// TODO: initiate values
		wait_time = `kWaitTime;
	end


	// update coin return time  i_input_coin, i_select_item, o_available_item
	always @(*) begin
		// TODO: update coin return time

		if(i_input_coin[0]==1) begin
			wait_time_nxt = `kWaitTime;
		end
		else if(i_input_coin[1]==1) begin
			wait_time_nxt = `kWaitTime;
		end
		else if(i_input_coin[2]==1) begin
			wait_time_nxt = `kWaitTime;
		end
		//select item 따라 시간 바꾸기
		else if(i_select_item[0]==1 && o_available_item[0]==1) begin
				wait_time_nxt = `kWaitTime;
		end

		else if(i_select_item[1]==1 && o_available_item[1]==1) begin
				wait_time_nxt = `kWaitTime;
		end

		else if(i_select_item[2]==1 && o_available_item[2]==1) begin
				wait_time_nxt = `kWaitTime;
		end

		else if(i_select_item[3]==1 && o_available_item[3]==1) begin
				wait_time_nxt = `kWaitTime;
		end
		else begin
			wait_time_nxt = wait_time-1;
		end
		
	end

	always @(posedge clk ) begin

		if (!reset_n) begin
		// TODO: reset all states.
			wait_time <= `kWaitTime;
		end
		else begin
		// TODO: update all states.
			wait_time <= wait_time_nxt;
		end
	end
endmodule

lab1/vending_machine2/vending_machine.v
// Title         : vending_machine.v
// Author      : Jae-Eon Jo (Jojaeeon@postech.ac.kr) 
//			     Dongup Kwon (nankdu7@postech.ac.kr) (2015.03.30)
//			     Jaehun Ryu (jaehunryu@postech.ac.kr) (2021.03.07)

`include "vending_machine_def.v"


module vending_machine (
	clk,							// Clock signal
	reset_n,						// Reset signal (active-low)

	i_input_coin,				// coin is inserted.
	i_select_item,				// item is selected.
	i_trigger_return,			// change-return is triggered 

	o_available_item,			// Sign of the item availability
	o_output_item,			// Sign of the item withdrawal
	o_return_coin			// Sign of the coin return
);
	// Ports Declaration
	// Do not modify the module interface
	input clk;
	input reset_n;
	
	input [`kNumCoins-1:0] i_input_coin;
	input [`kNumItems-1:0] i_select_item;
	input i_trigger_return;
		
	output [`kNumItems-1:0] o_available_item;
	output [`kNumItems-1:0] o_output_item;
	output [`kNumCoins-1:0] o_return_coin;

	// Do not modify the values.
	wire [31:0] item_price [`kNumItems-1:0];	// Price of each item
	wire [31:0] coin_value [`kNumCoins-1:0];	// Value of each coin
	assign item_price[0] = 400;
	assign item_price[1] = 500;
	assign item_price[2] = 1000;
	assign item_price[3] = 2000;
	assign coin_value[0] = 100;
	assign coin_value[1] = 500;
	assign coin_value[2] = 1000;

	// Internal states. You may add your own net variables.
	wire [`kTotalBits-1:0] current_total;
	
	// Next internal states. You may add your own net variables.
	wire [`kTotalBits-1:0] current_total_nxt;

	// Variables. You may add more your own net variables.
	wire [31:0] wait_time;
	reg [`kNumCoins-1:0] return_coin_nxt;
	


	// This module interface, structure, and given a number of modules are not mandatory but recommended.
	// However, Implementations that use modules are mandatory.

  	check_time_and_coin check_time_and_coin_module(.i_input_coin(i_input_coin),
  									.i_select_item(i_select_item),
									.o_available_item(o_available_item),
									.clk(clk),
									.reset_n(reset_n),
									.wait_time(wait_time));


	calculate_current_state calculate_current_state_module(
										.i_input_coin(i_input_coin),
										.i_select_item(i_select_item),
										.i_trigger_return(i_trigger_return),
										.item_price(item_price),
										.coin_value(coin_value),
										.current_total(current_total),
										.current_total_nxt(current_total_nxt),
										.wait_time(wait_time),
										.o_available_item(o_available_item),
										.o_output_item(o_output_item),
										.return_coin_nxt(return_coin_nxt));
	

  	change_state change_state_module(
						.clk(clk),
						.reset_n(reset_n),
						.current_total_nxt(current_total_nxt),
						.current_total(current_total),
						.return_coin_nxt(return_coin_nxt),
						.o_return_coin(o_return_coin));


endmodule

lab1/vending_machine2/waveform.vcd
$version Generated by VerilatedVcd $end
$timescale 1ps $end
 $scope module TOP $end
  $var wire 1 * clk $end
  $var wire 1 + reset_n $end
  $var wire 3 , i_input_coin [2:0] $end
  $var wire 4 - i_select_item [3:0] $end
  $var wire 1 . i_trigger_return $end
  $var wire 4 / o_available_item [3:0] $end
  $var wire 4 0 o_output_item [3:0] $end
  $var wire 3 1 o_return_coin [2:0] $end
  $scope module vending_machine $end
   $var wire 1 * clk $end
   $var wire 1 + reset_n $end
   $var wire 3 , i_input_coin [2:0] $end
   $var wire 4 - i_select_item [3:0] $end
   $var wire 1 . i_trigger_return $end
   $var wire 4 / o_available_item [3:0] $end
   $var wire 4 0 o_output_item [3:0] $end
   $var wire 3 1 o_return_coin [2:0] $end
   $var wire 32 # item_price[0] [31:0] $end
   $var wire 32 $ item_price[1] [31:0] $end
   $var wire 32 % item_price[2] [31:0] $end
   $var wire 32 & item_price[3] [31:0] $end
   $var wire 32 ' coin_value[0] [31:0] $end
   $var wire 32 ( coin_value[1] [31:0] $end
   $var wire 32 ) coin_value[2] [31:0] $end
   $var wire 32 2 current_total [31:0] $end
   $var wire 32 3 current_total_nxt [31:0] $end
   $var wire 32 4 wait_time [31:0] $end
   $var wire 3 5 return_coin_nxt [2:0] $end
   $scope module calculate_current_state_module $end
    $var wire 3 , i_input_coin [2:0] $end
    $var wire 4 - i_select_item [3:0] $end
    $var wire 1 . i_trigger_return $end
    $var wire 32 # item_price[0] [31:0] $end
    $var wire 32 $ item_price[1] [31:0] $end
    $var wire 32 % item_price[2] [31:0] $end
    $var wire 32 & item_price[3] [31:0] $end
    $var wire 32 ' coin_value[0] [31:0] $end
    $var wire 32 ( coin_value[1] [31:0] $end
    $var wire 32 ) coin_value[2] [31:0] $end
    $var wire 32 2 current_total [31:0] $end
    $var wire 32 4 wait_time [31:0] $end
    $var wire 4 / o_available_item [3:0] $end
    $var wire 4 0 o_output_item [3:0] $end
    $var wire 32 3 current_total_nxt [31:0] $end
    $var wire 3 5 return_coin_nxt [2:0] $end
    $var wire 32 6 i [31:0] $end
   $upscope $end
   $scope module change_state_module $end
    $var wire 1 * clk $end
    $var wire 1 + reset_n $end
    $var wire 32 3 current_total_nxt [31:0] $end
    $var wire 3 5 return_coin_nxt [2:0] $end
    $var wire 3 1 o_return_coin [2:0] $end
    $var wire 32 2 current_total [31:0] $end
   $upscope $end
   $scope module check_time_and_coin_module $end
    $var wire 1 * clk $end
    $var wire 1 + reset_n $end
    $var wire 3 , i_input_coin [2:0] $end
    $var wire 4 - i_select_item [3:0] $end
    $var wire 4 / o_available_item [3:0] $end
    $var wire 32 4 wait_time [31:0] $end
    $var wire 32 7 wait_time_nxt [31:0] $end
   $upscope $end
  $upscope $end
 $upscope $end
$enddefinitions $end


#0
b00000000000000000000000110010000 #
b00000000000000000000000111110100 $
b00000000000000000000001111101000 %
b00000000000000000000011111010000 &
b00000000000000000000000001100100 '
b00000000000000000000000111110100 (
b00000000000000000000001111101000 )
1*
1+
b000 ,
b0000 -
0.
b1111 /
b0000 0
b000 1
b11000110010101111110111011101001 2
b11000110010101111110111011101001 3
b00000000000000000000000000001010 4
b000 5
b00000000000000000000000000000000 6
b00000000000000000000000000001001 7
#1
0*
#2
1*
0+
b0000 /
b00000000000000000000000000000000 2
b00000000000000000000000000000000 3
#3
0*
#4
1*
#5
0*
#6
1*
1+
b00000000000000000000000000001001 4
b00000000000000000000000000001000 7
#7
0*
#8
1*
b001 ,
b00000000000000000000000001100100 2
b00000000000000000000000011001000 3
b00000000000000000000000000001010 4
b00000000000000000000000000001010 7
#9
0*
#10
1*
b000 ,
b00000000000000000000000001100100 3
b00000000000000000000000000001001 4
b00000000000000000000000000001000 7
#11
0*
#12
1*
b001 ,
b00000000000000000000000011001000 2
b00000000000000000000000100101100 3
b00000000000000000000000000001010 4
b00000000000000000000000000001010 7
#13
0*
#14
1*
b000 ,
b00000000000000000000000011001000 3
b00000000000000000000000000001001 4
b00000000000000000000000000001000 7
#15
0*
#16
1*
b001 ,
b00000000000000000000000100101100 2
b00000000000000000000000110010000 3
b00000000000000000000000000001010 4
b00000000000000000000000000001010 7
#17
0*
#18
1*
b000 ,
b00000000000000000000000100101100 3
b00000000000000000000000000001001 4
b00000000000000000000000000001000 7
#19
0*
#20
1*
b001 ,
b0001 /
b00000000000000000000000110010000 2
b00000000000000000000000111110100 3
b00000000000000000000000000001010 4
b00000000000000000000000000001010 7
#21
0*
#22
1*
b000 ,
b00000000000000000000000110010000 3
b00000000000000000000000000001001 4
b00000000000000000000000000001000 7
#23
0*
#24
1*
b001 ,
b0011 /
b00000000000000000000000111110100 2
b00000000000000000000001001011000 3
b00000000000000000000000000001010 4
b00000000000000000000000000001010 7
#25
0*
#26
1*
b000 ,
b00000000000000000000000111110100 3
b00000000000000000000000000001001 4
b00000000000000000000000000001000 7
#27
0*
#28
1*
b00000000000000000000000000001000 4
b00000000000000000000000000000111 7
#29
0*
#30
1*
0+
b0000 /
b00000000000000000000000000000000 2
b00000000000000000000000000000000 3
b00000000000000000000000000001010 4
b00000000000000000000000000001001 7
#31
0*
#32
1*
#33
0*
#34
1*
1+
b00000000000000000000000000001001 4
b00000000000000000000000000001000 7
#35
0*
#36
1*
b010 ,
b0011 /
b00000000000000000000000111110100 2
b00000000000000000000001111101000 3
b00000000000000000000000000001010 4
b00000000000000000000000000001010 7
#37
0*
#38
1*
b000 ,
b00000000000000000000000111110100 3
b00000000000000000000000000001001 4
b00000000000000000000000000001000 7
#39
0*
#40
1*
b010 ,
b0111 /
b00000000000000000000001111101000 2
b00000000000000000000010111011100 3
b00000000000000000000000000001010 4
b00000000000000000000000000001010 7
#41
0*
#42
1*
b000 ,
b00000000000000000000001111101000 3
b00000000000000000000000000001001 4
b00000000000000000000000000001000 7
#43
0*
#44
1*
b010 ,
b00000000000000000000010111011100 2
b00000000000000000000011111010000 3
b00000000000000000000000000001010 4
b00000000000000000000000000001010 7
#45
0*
#46
1*
b000 ,
b00000000000000000000010111011100 3
b00000000000000000000000000001001 4
b00000000000000000000000000001000 7
#47
0*
#48
1*
b010 ,
b1111 /
b00000000000000000000011111010000 2
b00000000000000000000100111000100 3
b00000000000000000000000000001010 4
b00000000000000000000000000001010 7
#49
0*
#50
1*
b000 ,
b00000000000000000000011111010000 3
b00000000000000000000000000001001 4
b00000000000000000000000000001000 7
#51
0*
#52
1*
b00000000000000000000000000001000 4
b00000000000000000000000000000111 7
#53
0*
#54
1*
0+
b0000 /
b00000000000000000000000000000000 2
b00000000000000000000000000000000 3
b00000000000000000000000000001010 4
b00000000000000000000000000001001 7
#55
0*
#56
1*
#57
0*
#58
1*
1+
b00000000000000000000000000001001 4
b00000000000000000000000000001000 7
#59
0*
#60
1*
b100 ,
b0111 /
b00000000000000000000001111101000 2
b00000000000000000000011111010000 3
b00000000000000000000000000001010 4
b00000000000000000000000000001010 7
#61
0*
#62
1*
b000 ,
b00000000000000000000001111101000 3
b00000000000000000000000000001001 4
b00000000000000000000000000001000 7
#63
0*
#64
1*
b100 ,
b1111 /
b00000000000000000000011111010000 2
b00000000000000000000101110111000 3
b00000000000000000000000000001010 4
b00000000000000000000000000001010 7
#65
0*
#66
1*
b000 ,
b00000000000000000000011111010000 3
b00000000000000000000000000001001 4
b00000000000000000000000000001000 7
#67
0*
#68
1*
b00000000000000000000000000001000 4
b00000000000000000000000000000111 7
#69
0*
#70
1*
0+
b0000 /
b00000000000000000000000000000000 2
b00000000000000000000000000000000 3
b00000000000000000000000000001010 4
b00000000000000000000000000001001 7
#71
0*
#72
1*
#73
0*
#74
1*
1+
b00000000000000000000000000001001 4
b00000000000000000000000000001000 7
#75
0*
#76
1*
b100 ,
b0111 /
b00000000000000000000001111101000 2
b00000000000000000000011111010000 3
b00000000000000000000000000001010 4
b00000000000000000000000000001010 7
#77
0*
#78
1*
b000 ,
b00000000000000000000001111101000 3
b00000000000000000000000000001001 4
b00000000000000000000000000001000 7
#79
0*
#80
1*
b100 ,
b1111 /
b00000000000000000000011111010000 2
b00000000000000000000101110111000 3
b00000000000000000000000000001010 4
b00000000000000000000000000001010 7
#81
0*
#82
1*
b000 ,
b00000000000000000000011111010000 3
b00000000000000000000000000001001 4
b00000000000000000000000000001000 7
#83
0*
#84
1*
b100 ,
b00000000000000000000101110111000 2
b00000000000000000000111110100000 3
b00000000000000000000000000001010 4
b00000000000000000000000000001010 7
#85
0*
#86
1*
b000 ,
b00000000000000000000101110111000 3
b00000000000000000000000000001001 4
b00000000000000000000000000001000 7
#87
0*
#88
1*
b0001 -
b0001 0
b00000000000000000000101000101000 2
b00000000000000000000100010011000 3
b00000000000000000000000000001010 4
b00000000000000000000000000001010 7
#89
0*
#90
1*
b0000 -
b0000 0
b00000000000000000000101000101000 3
b00000000000000000000000000001001 4
b00000000000000000000000000001000 7
#91
0*
#92
1*
b00000000000000000000000000001000 4
b00000000000000000000000000000111 7
#93
0*
#94
1*
b00000000000000000000000000000111 4
b00000000000000000000000000000110 7
#95
0*
#96
1*
b0001 -
b0001 0
b00000000000000000000100010011000 2
b00000000000000000000011100001000 3
b00000000000000000000000000001010 4
b00000000000000000000000000001010 7
#97
0*
#98
1*
b0000 -
b0000 0
b00000000000000000000100010011000 3
b00000000000000000000000000001001 4
b00000000000000000000000000001000 7
#99
0*
#100
1*
b00000000000000000000000000001000 4
b00000000000000000000000000000111 7
#101
0*
#102
1*
b00000000000000000000000000000111 4
b00000000000000000000000000000110 7
#103
0*
#104
1*
b0001 -
b0111 /
b0001 0
b00000000000000000000011100001000 2
b00000000000000000000010101111000 3
b00000000000000000000000000001010 4
b00000000000000000000000000001010 7
#105
0*
#106
1*
b0000 -
b0000 0
b00000000000000000000011100001000 3
b00000000000000000000000000001001 4
b00000000000000000000000000001000 7
#107
0*
#108
1*
b00000000000000000000000000001000 4
b00000000000000000000000000000111 7
#109
0*
#110
1*
b00000000000000000000000000000111 4
b00000000000000000000000000000110 7
#111
0*
#112
1*
b0001 -
b0001 0
b00000000000000000000010101111000 2
b00000000000000000000001111101000 3
b00000000000000000000000000001010 4
b00000000000000000000000000001010 7
#113
0*
#114
1*
b0000 -
b0000 0
b00000000000000000000010101111000 3
b00000000000000000000000000001001 4
b00000000000000000000000000001000 7
#115
0*
#116
1*
b00000000000000000000000000001000 4
b00000000000000000000000000000111 7
#117
0*
#118
1*
b00000000000000000000000000000111 4
b00000000000000000000000000000110 7
#119
0*
#120
1*
b0001 -
b0001 0
b00000000000000000000001111101000 2
b00000000000000000000001001011000 3
b00000000000000000000000000001010 4
b00000000000000000000000000001010 7
#121
0*
#122
1*
b0000 -
b0000 0
b00000000000000000000001111101000 3
b00000000000000000000000000001001 4
b00000000000000000000000000001000 7
#123
0*
#124
1*
b00000000000000000000000000001000 4
b00000000000000000000000000000111 7
#125
0*
#126
1*
b00000000000000000000000000000111 4
b00000000000000000000000000000110 7
#127
0*
#128
1*
b0001 -
b0011 /
b0001 0
b00000000000000000000001001011000 2
b00000000000000000000000011001000 3
b00000000000000000000000000001010 4
b00000000000000000000000000001010 7
#129
0*
#130
1*
b0000 -
b0000 0
b00000000000000000000001001011000 3
b00000000000000000000000000001001 4
b00000000000000000000000000001000 7
#131
0*
#132
1*
b00000000000000000000000000001000 4
b00000000000000000000000000000111 7
#133
0*
#134
1*
b00000000000000000000000000000111 4
b00000000000000000000000000000110 7
#135
0*
#136
1*
b0001 -
b0000 /
b00000000000000000000000011001000 2
b00000000000000000000000011001000 3
b00000000000000000000000000001010 4
b00000000000000000000000000001001 7
#137
0*
#138
1*
b0000 -
b00000000000000000000000000001001 4
b00000000000000000000000000001000 7
#139
0*
#140
1*
b00000000000000000000000000001000 4
b00000000000000000000000000000111 7
#141
0*
#142
1*
b00000000000000000000000000000111 4
b00000000000000000000000000000110 7
#143
0*
#144
1*
b00000000000000000000000000000110 4
b00000000000000000000000000000101 7
#145
0*
#146
1*
b00000000000000000000000000000101 4
b00000000000000000000000000000100 7
#147
0*
#148
1*
b100 ,
b0111 /
b00000000000000000000010010110000 2
b00000000000000000000100010011000 3
b00000000000000000000000000001010 4
b00000000000000000000000000001010 7
#149
0*
#150
1*
b000 ,
b00000000000000000000010010110000 3
b00000000000000000000000000001001 4
b00000000000000000000000000001000 7
#151
0*
#152
1*
b100 ,
b1111 /
b00000000000000000000100010011000 2
b00000000000000000000110010000000 3
b00000000000000000000000000001010 4
b00000000000000000000000000001010 7
#153
0*
#154
1*
b000 ,
b00000000000000000000100010011000 3
b00000000000000000000000000001001 4
b00000000000000000000000000001000 7
#155
0*
#156
1*
b100 ,
b00000000000000000000110010000000 2
b00000000000000000001000001101000 3
b00000000000000000000000000001010 4
b00000000000000000000000000001010 7
#157
0*
#158
1*
b000 ,
b00000000000000000000110010000000 3
b00000000000000000000000000001001 4
b00000000000000000000000000001000 7
#159
0*
#160
1*
b0010 -
b0010 0
b00000000000000000000101010001100 2
b00000000000000000000100010011000 3
b00000000000000000000000000001010 4
b00000000000000000000000000001010 7
#161
0*
#162
1*
b0000 -
b0000 0
b00000000000000000000101010001100 3
b00000000000000000000000000001001 4
b00000000000000000000000000001000 7
#163
0*
#164
1*
b00000000000000000000000000001000 4
b00000000000000000000000000000111 7
#165
0*
#166
1*
b00000000000000000000000000000111 4
b00000000000000000000000000000110 7
#167
0*
#168
1*
b0010 -
b0010 0
b00000000000000000000100010011000 2
b00000000000000000000011010100100 3
b00000000000000000000000000001010 4
b00000000000000000000000000001010 7
#169
0*
#170
1*
b0000 -
b0000 0
b00000000000000000000100010011000 3
b00000000000000000000000000001001 4
b00000000000000000000000000001000 7
#171
0*
#172
1*
b00000000000000000000000000001000 4
b00000000000000000000000000000111 7
#173
0*
#174
1*
b00000000000000000000000000000111 4
b00000000000000000000000000000110 7
#175
0*
#176
1*
b0010 -
b0111 /
b0010 0
b00000000000000000000011010100100 2
b00000000000000000000010010110000 3
b00000000000000000000000000001010 4
b00000000000000000000000000001010 7
#177
0*
#178
1*
b0000 -
b0000 0
b00000000000000000000011010100100 3
b00000000000000000000000000001001 4
b00000000000000000000000000001000 7
#179
0*
#180
1*
b00000000000000000000000000001000 4
b00000000000000000000000000000111 7
#181
0*
#182
1*
b00000000000000000000000000000111 4
b00000000000000000000000000000110 7
#183
0*
#184
1*
b0010 -
b0010 0
b00000000000000000000010010110000 2
b00000000000000000000001010111100 3
b00000000000000000000000000001010 4
b00000000000000000000000000001010 7
#185
0*
#186
1*
b0000 -
b0000 0
b00000000000000000000010010110000 3
b00000000000000000000000000001001 4
b00000000000000000000000000001000 7
#187
0*
#188
1*
b00000000000000000000000000001000 4
b00000000000000000000000000000111 7
#189
0*
#190
1*
b00000000000000000000000000000111 4
b00000000000000000000000000000110 7
#191
0*
#192
1*
b0010 -
b0011 /
b0010 0
b00000000000000000000001010111100 2
b00000000000000000000000011001000 3
b00000000000000000000000000001010 4
b00000000000000000000000000001010 7
#193
0*
#194
1*
b0000 -
b0000 0
b00000000000000000000001010111100 3
b00000000000000000000000000001001 4
b00000000000000000000000000001000 7
#195
0*
#196
1*
b00000000000000000000000000001000 4
b00000000000000000000000000000111 7
#197
0*
#198
1*
b00000000000000000000000000000111 4
b00000000000000000000000000000110 7
#199
0*
#200
1*
b0010 -
b0000 /
b00000000000000000000000011001000 2
b00000000000000000000000011001000 3
b00000000000000000000000000001010 4
b00000000000000000000000000001001 7
#201
0*
#202
1*
b0000 -
b00000000000000000000000000001001 4
b00000000000000000000000000001000 7
#203
0*
#204
1*
b00000000000000000000000000001000 4
b00000000000000000000000000000111 7
#205
0*
#206
1*
b00000000000000000000000000000111 4
b00000000000000000000000000000110 7
#207
0*
#208
1*
b001 ,
b00000000000000000000000100101100 2
b00000000000000000000000110010000 3
b00000000000000000000000000001010 4
b00000000000000000000000000001010 7
#209
0*
#210
1*
b000 ,
b00000000000000000000000100101100 3
b00000000000000000000000000001001 4
b00000000000000000000000000001000 7
#211
0*
#212
1*
b001 ,
b0001 /
b00000000000000000000000110010000 2
b00000000000000000000000111110100 3
b00000000000000000000000000001010 4
b00000000000000000000000000001010 7
#213
0*
#214
1*
b000 ,
b00000000000000000000000110010000 3
b00000000000000000000000000001001 4
b00000000000000000000000000001000 7
#215
0*
#216
1*
b100 ,
b0111 /
b00000000000000000000010101111000 2
b00000000000000000000100101100000 3
b00000000000000000000000000001010 4
b00000000000000000000000000001010 7
#217
0*
#218
1*
b000 ,
b00000000000000000000010101111000 3
b00000000000000000000000000001001 4
b00000000000000000000000000001000 7
#219
0*
#220
1*
b100 ,
b1111 /
b00000000000000000000100101100000 2
b00000000000000000000110101001000 3
b00000000000000000000000000001010 4
b00000000000000000000000000001010 7
#221
0*
#222
1*
b000 ,
b00000000000000000000100101100000 3
b00000000000000000000000000001001 4
b00000000000000000000000000001000 7
#223
0*
#224
1*
b100 ,
b00000000000000000000110101001000 2
b00000000000000000001000100110000 3
b00000000000000000000000000001010 4
b00000000000000000000000000001010 7
#225
0*
#226
1*
b000 ,
b00000000000000000000110101001000 3
b00000000000000000000000000001001 4
b00000000000000000000000000001000 7
#227
0*
#228
1*
b0100 -
b0100 0
b00000000000000000000100101100000 2
b00000000000000000000010101111000 3
b00000000000000000000000000001010 4
b00000000000000000000000000001010 7
#229
0*
#230
1*
b0000 -
b0000 0
b00000000000000000000100101100000 3
b00000000000000000000000000001001 4
b00000000000000000000000000001000 7
#231
0*
#232
1*
b00000000000000000000000000001000 4
b00000000000000000000000000000111 7
#233
0*
#234
1*
b00000000000000000000000000000111 4
b00000000000000000000000000000110 7
#235
0*
#236
1*
b0100 -
b0111 /
b0100 0
b00000000000000000000010101111000 2
b00000000000000000000000110010000 3
b00000000000000000000000000001010 4
b00000000000000000000000000001010 7
#237
0*
#238
1*
b0000 -
b0000 0
b00000000000000000000010101111000 3
b00000000000000000000000000001001 4
b00000000000000000000000000001000 7
#239
0*
#240
1*
b00000000000000000000000000001000 4
b00000000000000000000000000000111 7
#241
0*
#242
1*
b00000000000000000000000000000111 4
b00000000000000000000000000000110 7
#243
0*
#244
1*
b0100 -
b0001 /
b00000000000000000000000110010000 2
b00000000000000000000000110010000 3
b00000000000000000000000000001010 4
b00000000000000000000000000001001 7
#245
0*
#246
1*
b0000 -
b00000000000000000000000000001001 4
b00000000000000000000000000001000 7
#247
0*
#248
1*
b00000000000000000000000000001000 4
b00000000000000000000000000000111 7
#249
0*
#250
1*
b00000000000000000000000000000111 4
b00000000000000000000000000000110 7
#251
0*
#252
1*
b100 ,
b0111 /
b00000000000000000000010101111000 2
b00000000000000000000100101100000 3
b00000000000000000000000000001010 4
b00000000000000000000000000001010 7
#253
0*
#254
1*
b000 ,
b00000000000000000000010101111000 3
b00000000000000000000000000001001 4
b00000000000000000000000000001000 7
#255
0*
#256
1*
b100 ,
b1111 /
b00000000000000000000100101100000 2
b00000000000000000000110101001000 3
b00000000000000000000000000001010 4
b00000000000000000000000000001010 7
#257
0*
#258
1*
b000 ,
b00000000000000000000100101100000 3
b00000000000000000000000000001001 4
b00000000000000000000000000001000 7
#259
0*
#260
1*
b100 ,
b00000000000000000000110101001000 2
b00000000000000000001000100110000 3
b00000000000000000000000000001010 4
b00000000000000000000000000001010 7
#261
0*
#262
1*
b000 ,
b00000000000000000000110101001000 3
b00000000000000000000000000001001 4
b00000000000000000000000000001000 7
#263
0*
#264
1*
b1000 -
b0111 /
b00000000000000000000010101111000 2
b00000000000000000000010101111000 3
b00000000000000000000000000001010 4
b00000000000000000000000000001001 7
#265
0*
#266
1*
b0000 -
b00000000000000000000000000001001 4
b00000000000000000000000000001000 7
#267
0*
#268
1*
b00000000000000000000000000001000 4
b00000000000000000000000000000111 7
#269
0*
#270
1*
b00000000000000000000000000000111 4
b00000000000000000000000000000110 7
#271
0*
#272
1*
b100 ,
b1111 /
b00000000000000000000100101100000 2
b00000000000000000000110101001000 3
b00000000000000000000000000001010 4
b00000000000000000000000000001010 7
#273
0*
#274
1*
b000 ,
b00000000000000000000100101100000 3
b00000000000000000000000000001001 4
b00000000000000000000000000001000 7
#275
0*
#276
1*
b1000 -
b0001 /
b00000000000000000000000110010000 2
b00000000000000000000000110010000 3
b00000000000000000000000000001010 4
b00000000000000000000000000001001 7
#277
0*
#278
1*
b0000 -
b00000000000000000000000000001001 4
b00000000000000000000000000001000 7
#279
0*
#280
1*
b00000000000000000000000000001000 4
b00000000000000000000000000000111 7
#281
0*
#282
1*
b00000000000000000000000000000111 4
b00000000000000000000000000000110 7
#283
0*
#284
1*
b001 ,
b0011 /
b00000000000000000000000111110100 2
b00000000000000000000001001011000 3
b00000000000000000000000000001010 4
b00000000000000000000000000001010 7
#285
0*
#286
1*
b000 ,
b00000000000000000000000111110100 3
b00000000000000000000000000001001 4
b00000000000000000000000000001000 7
#287
0*
#288
1*
b001 ,
b00000000000000000000001001011000 2
b00000000000000000000001010111100 3
b00000000000000000000000000001010 4
b00000000000000000000000000001010 7
#289
0*
